cell_voyager/__init__.py
cell_voyager-0.0.0.dist-info/LICENSE
cell_voyager-0.0.0.dist-info/METADATA
cell_voyager-0.0.0.dist-info/WHEEL
cell_voyager-0.0.0.dist-info/top_level.txt
cell_voyager-0.0.0.dist-info/RECORD
