Metadata-Version: 2.1
Name: cell-voyager
Version: 0.0.0
Summary: Voyager for cell data.
Author: Michael E. Vinyard
Author-email: mvinyard.ai@gmail.com
License: MIT
Classifier: Development Status :: 2 - Pre-Alpha
Classifier: Programming Language :: Python :: 3.9
Classifier: Intended Audience :: Science/Research
Classifier: Topic :: Scientific/Engineering :: Bio-Informatics
Requires-Python: >3.9.0
License-File: LICENSE
